COGCCpy/__init__.py
COGCCpy/production.py
COGCCpy/tops.py
COGCCpy-0.0.3.dist-info/METADATA
COGCCpy-0.0.3.dist-info/WHEEL
COGCCpy-0.0.3.dist-info/licence.txt
COGCCpy-0.0.3.dist-info/top_level.txt
COGCCpy-0.0.3.dist-info/RECORD
