Metadata-Version: 2.1
Name: COGCCpy
Version: 0.0.3
Summary: A python package to easily access COGCC data.
Home-page: https://github.com/Rocks-n-Code/COGCCpy
Author: Matthew W. Bauer, P.G.
Author-email: matthew.w.bauer.pg@gmail.com
License: MIT
Platform: UNKNOWN
Classifier: Development Status :: 3 - Alpha
Classifier: License :: OSI Approved :: MIT License
Classifier: Operating System :: OS Independent
Classifier: Programming Language :: Python :: 3
Classifier: Topic :: Scientific/Engineering
Requires-Python: >=3.6
Requires-Dist: requests (>=2.23.0)
Requires-Dist: pandas (>=1.0.3)
